setup.py
lollygag/.version
lollygag/__init__.py
lollygag.egg-info/PKG-INFO
lollygag.egg-info/SOURCES.txt
lollygag.egg-info/dependency_links.txt
lollygag.egg-info/requires.txt
lollygag.egg-info/top_level.txt
lollygag/core/__init__.py
lollygag/core/domain_crawler.py
lollygag/core/domain_crawler_test.py
lollygag/core/mapper_crawler.py
lollygag/core/mapper_crawler_test.py
lollygag/core/single_site/__init__.py
lollygag/core/single_site/crawler_base.py
lollygag/core/single_site/link_crawler.py
lollygag/core/single_site/link_crawler_test.py
lollygag/dependency_injection/__init__.py
lollygag/dependency_injection/inject.py
lollygag/dependency_injection/inject_test.py
lollygag/dependency_injection/requirements.py
lollygag/services/__init__.py
lollygag/services/config_service.py
lollygag/services/print_service.py
lollygag/services/services.py
lollygag/services/work/__init__.py
lollygag/services/work/work_service.py
lollygag/services/work/work_service_test.py
lollygag/utility/__init__.py
lollygag/utility/cleanable_thread.py
lollygag/utility/test_utils.py
lollygag/utility/url.py
lollygag/utility/url_test.py
lollygag/utility/observer/__init__.py
lollygag/utility/observer/observer.py
lollygag/utility/observer/subject.py
lollygag/utility/observer/subject_test.py
test/__init__.py
test/crawler_example.py
test/e2e_test.py
test/mapper_example.py
test/test_page/__init__.py
test/test_page/server.py