Metadata-Version: 1.0
Name: lollygag
Version: 0.2.0
Summary: A simple web crawling module
Home-page: https://github.com/snorrwe/lollygag
Author: Daniel Kiss
Author-email: littlesnorrboy@gmail.com
License: MIT
Platform: UNKNOWN
